[{"id": "569f7bbb51f7c7732aabcb31f72b3df83db14c04", "text": "Purslain, White and Red.\n\nThese differ very little, if any thing, from those in England, except in the Rankness of their Growth here.\n\nThey are generally boiled and used, when more valuable Greens are not in Plenty.\n\nThe Arabian Jessammy; Lat. Jasminum sive Sambac Arabum.\n\nThis is a woody creeping Vine, cloathed with dark-green sharp-pointed Leaves, of about Two Inches long, and one broad, bearing Seven-leaved white fragrant Flowers.\n\nThese are supported by Seven very sharp-pointed graminous Leaves.\n\nThis is planted chiefly in Gardens, or near Dwelling-houses.\n\nIt yields a very agreeable fragrant Smell, and keeps its Verdure all the Year.\n\nTithymaloides.\n\nThe Roots of this are very numerous and strong.\n\nThe main Stalk branches near the Earth, into many spiral strong Twigs.\n\nThe Bark of the Trunk, near the Roots, is smooth and whitish; but all its Branches of a deep shining Green, keeping their grateful Verdure undiminished thro' every Season of the Year.\n\nThese are cloathed with thick succulent green round-pointed Leaves, of about Four Inches long, and Two in Breadth, having their smooth Edges a little tinged with Yellow.\n\nThese are likewise set on the Branches alternately.\n\nThe Flower, which is of a fine deep Red, cannot be reduced to any Class that hath hitherto been described by any Botanical Writer, it being a triangular sharp-pointed small horizontal Sheath; the Top of the Pistil jutting out, making the Extremity of the longest Angle: This, on the Inside of the Flower, is covered with a yellow farinaceous Dust.\n\nFrom the same narrow Aperture appear several small Stamina, tipped with green Apices.\n\nThese Flowers are succeeded by triangular small Berries, of a dark Red when ripe.\n\nEach of these incloses Three angular Seeds.\n\nThe Berries, Branches, and Leaves, are full of a thick glutinous milky Juice.\n\nThe only Place that I have seen this was at Cluff's Bay, in St. Lucy's Parish.\n\nThis very seldom grows in any other Part of the Island.", "source": "olmocr", "added": "2025-10-03", "created": "2025-10-03", "metadata": {"Source-File": "/home/jic823/projects/def-jic823/pdfs_jacob/Hughes - 1750 - The Natural History of Barbados in Ten Books_page_211.pdf", "olmocr-version": "0.3.4", "pdf-total-pages": 1, "total-input-tokens": 1292, "total-output-tokens": 488, "total-fallback-pages": 0}, "attributes": {"pdf_page_numbers": [[0, 1972, 1]], "primary_language": ["en"], "is_rotation_valid": [true], "rotation_correction": [0], "is_table": [false], "is_diagram": [false]}}]