[{"id": "7308a7948134a14ff3e1a0f8cf2c33a794ada7de", "text": "comes to be removed, it flows copiously into the Bowels insomuch that in some of the first Days we generally find the new born Babe to be much Griped, and have frequently greenish Bilious Stooles, (called by Nurses Loosness) which are owing to the great irritation of that stimulating Liquor the Bile.\n\nAnother Argument of Proof of what I have Advanced concerning the force of the Bile, may be taken from what is notoriously observed in many old People of both Sexes, for it is certain that all the Juices of such are commonly ranker and more acrid than in younger People, as appears by their Spitle, Sweat, Urine, Faeces &c. And consequently in such the Bile must be sharper, and more Vellicating (Ceteris paribus)", "source": "olmocr", "added": "2025-10-03", "created": "2025-10-03", "metadata": {"Source-File": "/home/jic823/projects/def-jic823/pdfs_jacob/Ingram - 1744 - An essay, on the nature, cause, and seat of dysentery's, in a letter to Dr. Henry Warren of Barbados_page_35.pdf", "olmocr-version": "0.3.4", "pdf-total-pages": 1, "total-input-tokens": 1292, "total-output-tokens": 201, "total-fallback-pages": 0}, "attributes": {"pdf_page_numbers": [[0, 715, 1]], "primary_language": ["en"], "is_rotation_valid": [true], "rotation_correction": [0], "is_table": [false], "is_diagram": [false]}}]