{
  "identifier": "QPP_1891120301",
  "adaptive_ocr": "true",
  "collection": [
    "peel_newspapers",
    "peel",
    "university_of_alberta_libraries",
    "toronto"
  ],
  "collective_title": "Qu'Appelle progress",
  "coverage": [
    "Canada;Saskatchewan;Qu'Appelle",
    "Canada;Saskatchewan;Whitewood",
    "Canada;Saskatchewan;Indian Head"
  ],
  "date": "1891-12-03",
  "description": "Page 1: \n \n - Local News \n \n - A Winnipeg Drummer Fined \n \n - One of the \"Get There\" Liberals \n \n - The Herchmer Investigation and Fair Play \n \n - Local News \n \n - Local News \n \n - Paper Read at the Recent Convention \n \n - Met Instant Death \n \nPage 2: \n \n - A Soap Eater \n \n - Immensity of Australia \n \n - At Life's Dawning \n \n - A Velvet Winter Ahead \n \n - The Working Man's Enemy \n \n - Fools Himself Who Thinks \n \n - A Mother's Example \n \n - A Railroad Manager \n \n - Local News \n \n - The Most Prolific Fruit \n \n - A Peacock Throne \n \n - Local News \n \n - The Miracle City \n \n - Burning the Pacific Forests \n \n - Aphorisms \n \n - Terrible Encounter with a Tiger \n \n - The Gobbler Was Lonesome \n \n - Like Lightning \n \nPage 3: \n \n - Ties, Human and Divine \n \n - A Famous Hunting-Place for Whale, and Its Dangers \n \n - A Transaction in Rain Making \n \n - Russia's Dead in Turkey \n \n - Freaks of Memory \n \n - Before the Fire \n \n - For and About Women \n \n - Fought Unde Napoleon \n \n - Russia the Aggressive Power \n \n - The Empress Frederick in Good Spirits \n \n - Owning up to It \n \n - What a Locomotive Runs Down \n \n - A Terrific Fight \n \n - Saving His Capital \n \n - Late British News \n \n - The Western Boom \n \n - Local News \n \nPage 4: \n \n - Home & gossip \n \n - Rose Valley \n \n - Union of Christian Endeavor Societies \n \n - Our Trade Relations \n \n - Council Minutes \n \n - Final Court of Revision \n \n - Whitewood \n \n - Massacres Confirmed \n \n - Winter Sports \n \n - On' Appelle Observatory \n \n - Qu' Appelle Markets \n \n \n",
  "extent": "v. : ill.",
  "genre": "Newspaper",
  "issuance": "continuing",
  "language": "English",
  "mediatype": "texts",
  "notes": "Weekly. Began with vol. I, no. 1 (Nov. 13, 1885); ceased with vol. 14, no. 10 (Dec. 22, 1898). -- Vol. 1, no. 1-11, Oct. 13-Dec. 22, 1898 include section titled: The Vedette.\n",
  "publisher": "James Weidman",
  "scanner": "Internet Archive Python library 2.3.0",
  "subject": "Qu'Appelle progress",
  "title": "Qu'Appelle progress (1891-12-03)",
  "uploader": "digitization.IAscript@ualberta.ca",
  "publicdate": "2023-09-06 02:49:53",
  "addeddate": "2023-09-06 02:49:53",
  "identifier-access": "http://archive.org/details/QPP_1891120301",
  "identifier-ark": "ark:/13960/s2zjghj31nf",
  "imagecount": "4",
  "ocr": "tesseract 5.3.0-3-g9920",
  "ocr_parameters": "-l eng",
  "ocr_module_version": "0.0.21",
  "ocr_detected_script": "Cyrillic",
  "ocr_detected_script_conf": "0.3937",
  "ocr_detected_lang": "en",
  "ocr_detected_lang_conf": "1.0000",
  "page_number_confidence": "0",
  "page_number_module_version": "1.0.3",
  "pdf_module_version": "0.0.23"
}