{
  "identifier": "QPP_1892011401",
  "adaptive_ocr": "true",
  "collection": [
    "peel_newspapers",
    "peel",
    "university_of_alberta_libraries",
    "toronto"
  ],
  "collective_title": "Qu'Appelle progress",
  "coverage": [
    "Canada;Saskatchewan;Qu'Appelle",
    "Canada;Saskatchewan;Whitewood",
    "Canada;Saskatchewan;Indian Head"
  ],
  "date": "1892-01-14",
  "description": "Page 1: \n \n - Local News \n \n - Local News \n \n - Local News \n \n - The School Meeting at Qu'Appelle \n \n - The Legislative Assembly \n \n - The Homestead Laws \n \n - Globe Must Apologise \n \n - Quappelle Markets \n \nPage 2: \n \n - Agricultural \n \n - Exoiting Time on a Ferry \n \n - British Columbia \n \n - Local News \n \n - Local News \n \n - Competition \n \n - A Cape Breton Miracle \n \n - The Cruise of the Will-O'-the-Wisp \n \n - A Wedding Present \n \n - The Work Was Performed \n \nPage 3: \n \n - Ties, Human and Divine \n \n - Personal \n \n - Insuring A \n \n - Talks Very Pleasantly of His Alaskan Trip \n \n - Found Gold and a Wife \n \n - The Undeveloped Northwest \n \n - A Hunter's Paradise \n \n - The Wonderful Metal \n \n - The Homely Bag Carpet \n \n - Before the Fire \n \n - Ho for The \n \n - To Ocean No Longer Trackless \n \n - Local News \n \nPage 4: \n \n - Home & Gossip \n \n - Indian Head \n \n - Sons of England Annual Dinner \n \n - Curling Competition \n \n - Assembly Notes \n \n - Local News \n \n \n",
  "extent": "v. : ill.",
  "genre": "Newspaper",
  "issuance": "continuing",
  "language": "English",
  "mediatype": "texts",
  "notes": "Weekly. Began with vol. I, no. 1 (Nov. 13, 1885); ceased with vol. 14, no. 10 (Dec. 22, 1898). -- Vol. 1, no. 1-11, Oct. 13-Dec. 22, 1898 include section titled: The Vedette.\n",
  "publisher": "James Weidman",
  "scanner": "Internet Archive Python library 2.3.0",
  "subject": "Qu'Appelle progress",
  "title": "Qu'Appelle progress (1892-01-14)",
  "uploader": "digitization.IAscript@ualberta.ca",
  "publicdate": "2023-09-06 02:54:31",
  "addeddate": "2023-09-06 02:54:31",
  "identifier-access": "http://archive.org/details/QPP_1892011401",
  "identifier-ark": "ark:/13960/s2bhw7hvn85",
  "imagecount": "4",
  "ocr": "tesseract 5.3.0-3-g9920",
  "ocr_parameters": "-l eng",
  "ocr_module_version": "0.0.21",
  "ocr_detected_script": "Latin",
  "ocr_detected_script_conf": "1.0000",
  "ocr_detected_lang": "en",
  "ocr_detected_lang_conf": "1.0000",
  "page_number_confidence": "61",
  "page_number_module_version": "1.0.3",
  "pdf_module_version": "0.0.23"
}