{
  "language": "eng",
  "scanningcenter": "uoft",
  "sponsor": "University of Toronto",
  "contributor": "Fisher - University of Toronto",
  "subject": [
    "Mortgage bonds",
    "Railroads"
  ],
  "title": "The Qu'Appelle, Long Lake & Saskatchewan Railroad and Steamboat Company, and Ernest Chaplin, and Pascoe St. Leger Grenfell, trustees : mortgage to secure bonds at the rate of $15,000 per mile.",
  "creator": [
    "Qu'Appelle, Long Lake and Saskatchewan Railroad and Steamboat Company",
    "Chaplin, Ernest",
    "Grenfell, Pascoe St. Leger"
  ],
  "collection": [
    "canadianpamphlets",
    "thomasfisher",
    "toronto",
    "university_of_toronto"
  ],
  "shiptracking": "fpam4",
  "call_number": "cap 03790",
  "publisher": "[S.1. : s.n.]",
  "description": [
    "At head of title: Dated 8th August, 1889",
    "Signed (p. 27): H.C. Hammond, President. R.A. Smith, Secretary",
    "32"
  ],
  "mediatype": "texts",
  "repub_state": "4",
  "page-progression": "lr",
  "publicdate": "2013-11-21 18:03:37",
  "date": "1889",
  "updatedate": "2013-11-21 19:02:49",
  "updater": "associate-angela-dugas@archive.org",
  "identifier": "quappellelonglak00quap",
  "uploader": "associate-angela-dugas@archive.org",
  "addeddate": "2013-11-21 19:02:51.674921",
  "scanner": "scribe4.toronto.archive.org",
  "notes": "No copyright page found. No table-of-contents pages found.",
  "repub_seconds": "65",
  "ppi": "500",
  "camera": "Canon EOS 5D Mark II",
  "operator": "associate-carrie-lounsbury@archive.org",
  "scandate": "20131122142817",
  "republisher": "associate-gabriel-areay@archive.org",
  "imagecount": "38",
  "foldoutcount": "0",
  "identifier-access": "http://archive.org/details/quappellelonglak00quap",
  "identifier-ark": "ark:/13960/t44r08s0b",
  "curation": "[curator]associate-eliza-zhang@archive.org[/curator][date]20131125194036[/date][state]approved[/state][comment]199[/comment]",
  "scanfee": "100",
  "sponsordate": "20131130",
  "invoice": "1005",
  "backup_location": "ia905800_6",
  "openlibrary_edition": "OL21522591M",
  "openlibrary_work": "OL13402603W",
  "external-identifier": "urn:oclc:record:1051735780",
  "oclc-id": "224879810",
  "associated-names": "Chaplin, Ernest; Grenfell, Pascoe St. Leger",
  "republisher_operator": "associate-gabriel-areay@archive.org",
  "republisher_date": "20131125165644",
  "ocr_module_version": "0.0.21",
  "ocr_converted": "abbyy-to-hocr 1.1.37",
  "page_number_confidence": "56",
  "page_number_module_version": "1.0.3"
}